{
  "date_updated": "2021-10-28T00:00:00",
  "postcode": "2262",
  "data": [
    {
      "date": "2021-07-18",
      "postcode": "2262",
      "AgeGroup": "50 to 69",
      "dose1": 1,
      "dose2": 0,
      "vaccines": 1
    },
    {
      "date": "2021-08-08",
      "postcode": "2262",
      "AgeGroup": "16 to 49",
      "dose1": 1,
      "dose2": 0,
      "vaccines": 1
    },
    {
      "date": "2021-08-08",
      "postcode": "2262",
      "AgeGroup": "50 to 69",
      "dose1": 0,
      "dose2": 1,
      "vaccines": 1
    },
    {
      "date": "2021-08-19",
      "postcode": "2262",
      "AgeGroup": "16 to 49",
      "dose1": 1,
      "dose2": 0,
      "vaccines": 1
    },
    {
      "date": "2021-08-30",
      "postcode": "2262",
      "AgeGroup": "16 to 49",
      "dose1": 1,
      "dose2": 0,
      "vaccines": 1
    },
    {
      "date": "2021-09-05",
      "postcode": "2262",
      "AgeGroup": "16 to 49",
      "dose1": 1,
      "dose2": 0,
      "vaccines": 1
    },
    {
      "date": "2021-09-08",
      "postcode": "2262",
      "AgeGroup": "16 to 49",
      "dose1": 0,
      "dose2": 1,
      "vaccines": 1
    },
    {
      "date": "2021-09-12",
      "postcode": "2262",
      "AgeGroup": "16 to 49",
      "dose1": 0,
      "dose2": 1,
      "vaccines": 1
    },
    {
      "date": "2021-09-20",
      "postcode": "2262",
      "AgeGroup": "16 to 49",
      "dose1": 0,
      "dose2": 1,
      "vaccines": 1
    },
    {
      "date": "2021-09-22",
      "postcode": "2262",
      "AgeGroup": "16 to 49",
      "dose1": 1,
      "dose2": 0,
      "vaccines": 1
    },
    {
      "date": "2021-10-06",
      "postcode": "2262",
      "AgeGroup": "16 to 49",
      "dose1": 1,
      "dose2": 0,
      "vaccines": 1
    },
    {
      "date": "2021-10-09",
      "postcode": "2262",
      "AgeGroup": "16 to 49",
      "dose1": 0,
      "dose2": 1,
      "vaccines": 1
    },
    {
      "date": "2021-10-13",
      "postcode": "2262",
      "AgeGroup": "16 to 49",
      "dose1": 0,
      "dose2": 1,
      "vaccines": 1
    },
    {
      "date": "2021-10-16",
      "postcode": "2262",
      "AgeGroup": "50 to 69",
      "dose1": 1,
      "dose2": 0,
      "vaccines": 1
    },
    {
      "date": "2021-10-20",
      "postcode": "2262",
      "AgeGroup": "16 to 49",
      "dose1": 0,
      "dose2": 0,
      "vaccines": 0
    }
  ]
}