{
  "date": "2021-10-07",
  "data": [
    {
      "SA3Name": "Augusta - Margaret River - Busselton",
      "c16_plus": 44759,
      "dose1": 32589,
      "dose2": 23437,
      "total_doses": 56026,
      "atleast_1dose_percent": 67.808988764044943820224719100,
      "full_vaccinated_percent": 48.766125676238035788597586350,
      "c12_plus": 48060
    },
    {
      "SA3Name": "Bunbury",
      "c16_plus": 82947,
      "dose1": 58844,
      "dose2": 42211,
      "total_doses": 101055,
      "atleast_1dose_percent": 66.059701157425598078067290100,
      "full_vaccinated_percent": 47.387092066414450419300156040,
      "c12_plus": 89077
    },
    {
      "SA3Name": "Manjimup",
      "c16_plus": 18767,
      "dose1": 13891,
      "dose2": 10152,
      "total_doses": 24043,
      "atleast_1dose_percent": 69.257615794984294759934187570,
      "full_vaccinated_percent": 50.615745126389789101061973380,
      "c12_plus": 20057
    },
    {
      "SA3Name": "Mandurah",
      "c16_plus": 84916,
      "dose1": 59855,
      "dose2": 42265,
      "total_doses": 102120,
      "atleast_1dose_percent": 66.387533274179236912156166810,
      "full_vaccinated_percent": 46.877772848269742679680567880,
      "c12_plus": 90160
    },
    {
      "SA3Name": "Cottesloe - Claremont",
      "c16_plus": 59450,
      "dose1": 54022,
      "dose2": 43892,
      "total_doses": 97914,
      "atleast_1dose_percent": 84.44236029699101211410707308,
      "full_vaccinated_percent": 68.608050019538882375928096910,
      "c12_plus": 63975
    },
    {
      "SA3Name": "Perth City",
      "c16_plus": 96988,
      "dose1": 77547,
      "dose2": 60990,
      "total_doses": 138537,
      "atleast_1dose_percent": 77.090623508827739780499443300,
      "full_vaccinated_percent": 60.631064100524892635597264200,
      "c12_plus": 100592
    },
    {
      "SA3Name": "Bayswater - Bassendean",
      "c16_plus": 69701,
      "dose1": 50581,
      "dose2": 36526,
      "total_doses": 87107,
      "atleast_1dose_percent": 69.367911460976178394613053200,
      "full_vaccinated_percent": 50.092571005389689647133041680,
      "c12_plus": 72917
    },
    {
      "SA3Name": "Mundaring",
      "c16_plus": 34973,
      "dose1": 25765,
      "dose2": 17129,
      "total_doses": 42894,
      "atleast_1dose_percent": 69.045449673062493300460928290,
      "full_vaccinated_percent": 45.902561903741022617643906100,
      "c12_plus": 37316
    },
    {
      "SA3Name": "Swan",
      "c16_plus": 113743,
      "dose1": 74233,
      "dose2": 48968,
      "total_doses": 123201,
      "atleast_1dose_percent": 61.001224412651716232096046540,
      "full_vaccinated_percent": 40.239623308215069314904142460,
      "c12_plus": 121691
    },
    {
      "SA3Name": "Joondalup",
      "c16_plus": 128189,
      "dose1": 106974,
      "dose2": 79890,
      "total_doses": 186864,
      "atleast_1dose_percent": 77.971660981369719233796903700,
      "full_vaccinated_percent": 58.230560657745123764541240270,
      "c12_plus": 137196
    },
    {
      "SA3Name": "Stirling",
      "c16_plus": 167769,
      "dose1": 125024,
      "dose2": 92489,
      "total_doses": 217513,
      "atleast_1dose_percent": 71.016591971553374344642684710,
      "full_vaccinated_percent": 52.535941698049974722946452410,
      "c12_plus": 176049
    },
    {
      "SA3Name": "Wanneroo",
      "c16_plus": 162448,
      "dose1": 108604,
      "dose2": 76163,
      "total_doses": 184767,
      "atleast_1dose_percent": 62.337274710136608885317414760,
      "full_vaccinated_percent": 43.716565262312019285960280110,
      "c12_plus": 174220
    },
    {
      "SA3Name": "Armadale",
      "c16_plus": 70740,
      "dose1": 45929,
      "dose2": 31878,
      "total_doses": 77807,
      "atleast_1dose_percent": 60.761486459670057812644696980,
      "full_vaccinated_percent": 42.172802921059942584238447390,
      "c12_plus": 75589
    },
    {
      "SA3Name": "Belmont - Victoria Park",
      "c16_plus": 64393,
      "dose1": 43807,
      "dose2": 32106,
      "total_doses": 75913,
      "atleast_1dose_percent": 65.693419710875172455161657970,
      "full_vaccinated_percent": 48.146481914702177433867194530,
      "c12_plus": 66684
    },
    {
      "SA3Name": "Canning",
      "c16_plus": 70900,
      "dose1": 54471,
      "dose2": 39725,
      "total_doses": 94196,
      "atleast_1dose_percent": 72.448328146197430372675764110,
      "full_vaccinated_percent": 52.835634293618492804511478200,
      "c12_plus": 75186
    },
    {
      "SA3Name": "Gosnells",
      "c16_plus": 97912,
      "dose1": 72208,
      "dose2": 49406,
      "total_doses": 121614,
      "atleast_1dose_percent": 69.280882705684816502758455270,
      "full_vaccinated_percent": 47.403214200047973135044375150,
      "c12_plus": 104225
    },
    {
      "SA3Name": "Kalamunda",
      "c16_plus": 47026,
      "dose1": 34658,
      "dose2": 24537,
      "total_doses": 59195,
      "atleast_1dose_percent": 69.008223323975071182525934330,
      "full_vaccinated_percent": 48.856101786034287079624873070,
      "c12_plus": 50223
    },
    {
      "SA3Name": "Serpentine - Jarrahdale",
      "c16_plus": 25420,
      "dose1": 14843,
      "dose2": 9958,
      "total_doses": 24801,
      "atleast_1dose_percent": 54.340106168771737140765147350,
      "full_vaccinated_percent": 36.456159619256818597840014640,
      "c12_plus": 27315
    },
    {
      "SA3Name": "South Perth",
      "c16_plus": 37509,
      "dose1": 28713,
      "dose2": 22490,
      "total_doses": 51203,
      "atleast_1dose_percent": 73.213830384007343566729562960,
      "full_vaccinated_percent": 57.346116579121831811923096540,
      "c12_plus": 39218
    },
    {
      "SA3Name": "Cockburn",
      "c16_plus": 90561,
      "dose1": 63746,
      "dose2": 45304,
      "total_doses": 109050,
      "atleast_1dose_percent": 66.380647915777196946819256280,
      "full_vaccinated_percent": 47.176432610302923014443252700,
      "c12_plus": 96031
    },
    {
      "SA3Name": "Fremantle",
      "c16_plus": 33168,
      "dose1": 27415,
      "dose2": 21186,
      "total_doses": 48601,
      "atleast_1dose_percent": 78.692806705321775073195935470,
      "full_vaccinated_percent": 60.812905448073942246971697570,
      "c12_plus": 34838
    },
    {
      "SA3Name": "Kwinana",
      "c16_plus": 35656,
      "dose1": 21546,
      "dose2": 15090,
      "total_doses": 36636,
      "atleast_1dose_percent": 56.857105158991951444781633460,
      "full_vaccinated_percent": 39.820556801688877160575273780,
      "c12_plus": 37895
    },
    {
      "SA3Name": "Melville",
      "c16_plus": 86448,
      "dose1": 74035,
      "dose2": 56697,
      "total_doses": 130732,
      "atleast_1dose_percent": 80.63936390371419235377409868,
      "full_vaccinated_percent": 61.754710815815270667683258900,
      "c12_plus": 91810
    },
    {
      "SA3Name": "Rockingham",
      "c16_plus": 106285,
      "dose1": 69350,
      "dose2": 48683,
      "total_doses": 118033,
      "atleast_1dose_percent": 60.712972528145956262146971790,
      "full_vaccinated_percent": 42.619893894559907551695761040,
      "c12_plus": 114226
    },
    {
      "SA3Name": "Albany",
      "c16_plus": 49102,
      "dose1": 35381,
      "dose2": 25026,
      "total_doses": 60407,
      "atleast_1dose_percent": 67.469488939740655987795575900,
      "full_vaccinated_percent": 47.723112128146453089244851260,
      "c12_plus": 52440
    },
    {
      "SA3Name": "Wheat Belt - North",
      "c16_plus": 45714,
      "dose1": 31113,
      "dose2": 21816,
      "total_doses": 52929,
      "atleast_1dose_percent": 63.988236019990539456635748510,
      "full_vaccinated_percent": 44.867655224893568887152170780,
      "c12_plus": 48623
    },
    {
      "SA3Name": "Wheat Belt - South",
      "c16_plus": 15726,
      "dose1": 11539,
      "dose2": 8374,
      "total_doses": 19913,
      "atleast_1dose_percent": 68.963662443222567535261773850,
      "full_vaccinated_percent": 50.047812574707147979918718620,
      "c12_plus": 16732
    },
    {
      "SA3Name": "Kimberley",
      "c16_plus": 26588,
      "dose1": 15789,
      "dose2": 10664,
      "total_doses": 26453,
      "atleast_1dose_percent": 54.874361380460848712334480240,
      "full_vaccinated_percent": 37.062523893928335592395648700,
      "c12_plus": 28773
    },
    {
      "SA3Name": "East Pilbara",
      "c16_plus": 20297,
      "dose1": 6944,
      "dose2": 4335,
      "total_doses": 11279,
      "atleast_1dose_percent": 32.535257461462774680223023940,
      "full_vaccinated_percent": 20.311109028721360633462962100,
      "c12_plus": 21343
    },
    {
      "SA3Name": "West Pilbara",
      "c16_plus": 28024,
      "dose1": 9437,
      "dose2": 5543,
      "total_doses": 14980,
      "atleast_1dose_percent": 31.832287661067260338662888750,
      "full_vaccinated_percent": 18.697294744653578897659043380,
      "c12_plus": 29646
    },
    {
      "SA3Name": "Esperance",
      "c16_plus": 12476,
      "dose1": 8494,
      "dose2": 5780,
      "total_doses": 14274,
      "atleast_1dose_percent": 63.530291697830964846671652950,
      "full_vaccinated_percent": 43.231114435302916978309648470,
      "c12_plus": 13370
    },
    {
      "SA3Name": "Gascoyne",
      "c16_plus": 7366,
      "dose1": 3977,
      "dose2": 2633,
      "total_doses": 6610,
      "atleast_1dose_percent": 50.837274702799437555924837020,
      "full_vaccinated_percent": 33.657164770548382973283906430,
      "c12_plus": 7823
    },
    {
      "SA3Name": "Goldfields",
      "c16_plus": 29316,
      "dose1": 15788,
      "dose2": 10709,
      "total_doses": 26497,
      "atleast_1dose_percent": 50.495746177956886074329943070,
      "full_vaccinated_percent": 34.251263353163180451608776310,
      "c12_plus": 31266
    },
    {
      "SA3Name": "Mid West",
      "c16_plus": 41477,
      "dose1": 28190,
      "dose2": 19175,
      "total_doses": 47365,
      "atleast_1dose_percent": 63.465261830789319645188887390,
      "full_vaccinated_percent": 43.169435814309514160925750820,
      "c12_plus": 44418
    },
    {
      "SA3Name": "Migratory - Offshore - Shipping (WA)",
      "c16_plus": 0,
      "dose1": 0,
      "dose2": 0,
      "total_doses": 0,
      "atleast_1dose_percent": 0.0,
      "full_vaccinated_percent": 0.0,
      "c12_plus": 0
    },
    {
      "SA3Name": "No usual address (WA)",
      "c16_plus": 0,
      "dose1": 8,
      "dose2": 2,
      "total_doses": 10,
      "atleast_1dose_percent": 0.0,
      "full_vaccinated_percent": 0.0,
      "c12_plus": 0
    },
    {
      "SA3Name": "Christmas Island",
      "c16_plus": 0,
      "dose1": 960,
      "dose2": 859,
      "total_doses": 1819,
      "atleast_1dose_percent": 0.0,
      "full_vaccinated_percent": 0.0,
      "c12_plus": 0
    },
    {
      "SA3Name": "Cocos (Keeling) Islands",
      "c16_plus": 0,
      "dose1": 378,
      "dose2": 330,
      "total_doses": 708,
      "atleast_1dose_percent": 0.0,
      "full_vaccinated_percent": 0.0,
      "c12_plus": 0
    },
    {
      "SA3Name": "Jervis Bay",
      "c16_plus": 0,
      "dose1": 0,
      "dose2": 0,
      "total_doses": 0,
      "atleast_1dose_percent": 0.0,
      "full_vaccinated_percent": 0.0,
      "c12_plus": 0
    },
    {
      "SA3Name": "Norfolk Island",
      "c16_plus": 0,
      "dose1": 0,
      "dose2": 0,
      "total_doses": 0,
      "atleast_1dose_percent": 0.0,
      "full_vaccinated_percent": 0.0,
      "c12_plus": 0
    },
    {
      "SA3Name": "Migratory - Offshore - Shipping (OT)",
      "c16_plus": 0,
      "dose1": 0,
      "dose2": 0,
      "total_doses": 0,
      "atleast_1dose_percent": 0.0,
      "full_vaccinated_percent": 0.0,
      "c12_plus": 0
    },
    {
      "SA3Name": "No usual address (OT)",
      "c16_plus": 0,
      "dose1": 0,
      "dose2": 0,
      "total_doses": 0,
      "atleast_1dose_percent": 0.0,
      "full_vaccinated_percent": 0.0,
      "c12_plus": 0
    }
  ]
}