{
  "date": "2021-10-04",
  "data": [
    {
      "Name": "Western Australia",
      "c16_plus": 2078985,
      "dose1": 1461299,
      "dose2": 1047300,
      "total_doses": 2508599,
      "atleast_1dose_percent": 66.166467211737820684359065960,
      "full_vaccinated_percent": 47.420918724267257832058497120,
      "c12_plus": 2208519
    },
    {
      "Name": "Other Territories",
      "c16_plus": 0,
      "dose1": 1331,
      "dose2": 1182,
      "total_doses": 2513,
      "atleast_1dose_percent": 0.0,
      "full_vaccinated_percent": 0.0,
      "c12_plus": 0
    }
  ]
}